uffspd/LICENSE
uffspd/README.MD
uffspd/__init__.py
uffspd/requirements.txt
uffspd/thirdparty.json
uffspd/uffs.com
uffspd-0.12.dist-info/LICENSE.rst
uffspd-0.12.dist-info/METADATA
uffspd-0.12.dist-info/WHEEL
uffspd-0.12.dist-info/top_level.txt
uffspd-0.12.dist-info/RECORD
