Metadata-Version: 2.1
Name: uffspd
Version: 0.12
Summary: Wrapper for the fastest file/folder list tool (UFFS) 350 GB in less than 3 Minutes (1.800.000 files and folders)
Home-page: https://github.com/hansalemaos/uffspd
Author: Johannes Fischer
Author-email: aulasparticularesdealemaosp@gmail.com
License: MIT
Keywords: ripgrep,grep,search,replace,regex,regular expressions,re,os.listdir,shutil,ls
Classifier: Development Status :: 4 - Beta
Classifier: Programming Language :: Python :: 3 :: Only
Classifier: Programming Language :: Python :: 3.10
Classifier: Topic :: Software Development :: Libraries :: Python Modules
Classifier: Topic :: Utilities
License-File: LICENSE.rst
Requires-Dist: a-pandas-ex-fast-string
Requires-Dist: a-pandas-ex-fastloc
Requires-Dist: numpy
Requires-Dist: pandas
Requires-Dist: Requests
Requires-Dist: touchtouch
